[{"id":"d56b6122-803e-47dc-9f74-141bc5a2db86","nom":"Test1","prenom":"test1","age":"01","promo":"0001","matricule":"BJGLI0001"},{"id":"2ea7b03f-a572-4300-8a6b-857fe8635ebe","nom":"Test3","prenom":"test3","age":"66","promo":"4000","matricule":"BJGLI0003"},{"id":"3676725d-d85f-46de-9536-007ca875bfdf","nom":"Test4","prenom":"test4","age":"77","promo":"2000","matricule":"BJGLI0004"},{"id":"9c3477dd-c4ef-4329-98cd-444a0e29b98b","nom":"Aurès","prenom":"dontPlay","age":"20","promo":"2000","matricule":"BJGLI0005"}]